observers-0.2.0.dist-info/METADATA
observers-0.2.0.dist-info/WHEEL
observers-0.2.0.dist-info/entry_points.txt
observers/__init__.py
observers/base.py
observers/frameworks/__init__.py
observers/models/__init__.py
observers/models/aisuite.py
observers/models/base.py
observers/models/hf_client.py
observers/models/litellm.py
observers/models/openai.py
observers/models/transformers.py
observers/stores/__init__.py
observers/stores/argilla.py
observers/stores/base.py
observers/stores/datasets.py
observers/stores/duckdb.py
observers/stores/migrations/001_create_schema_version.sql
observers/stores/migrations/002_add_arguments_field.sql
observers/stores/migrations/__init__.py
observers/stores/opentelemetry.py
observers/stores/sql_base.py
observers-0.2.0.dist-info/RECORD
