Metadata-Version: 2.1
Name: observers
Version: 0.2.0
Summary: 🤗 Observers: A Lightweight Library for AI Observability
Author-Email: davidberenstein1957 <david.m.berenstein@gmail.com>
License: Apache 2
Requires-Python: <3.13,>=3.10
Requires-Dist: duckdb>=1.0.0
Requires-Dist: datasets>=3.0.0
Requires-Dist: openai>=1.50.0
Requires-Dist: argilla>=2.3.0
Provides-Extra: aisuite
Requires-Dist: aisuite[all]>=0.1.6; extra == "aisuite"
Provides-Extra: dev
Requires-Dist: pytest>=8.3.3; extra == "dev"
Requires-Dist: black>=24.10.0; extra == "dev"
Requires-Dist: jinja2>=3.1.4; extra == "dev"
Requires-Dist: pytest-asyncio>=0.25.1; extra == "dev"
Provides-Extra: litellm
Requires-Dist: litellm>=1.52; extra == "litellm"
Provides-Extra: transformers
Requires-Dist: transformers>=4.46.0; extra == "transformers"
Requires-Dist: torch>=2; extra == "transformers"
Provides-Extra: opentelemetry
Requires-Dist: opentelemetry-api>=1.28.0; extra == "opentelemetry"
Requires-Dist: opentelemetry-sdk>=1.28.0; extra == "opentelemetry"
Requires-Dist: opentelemetry-exporter-otlp-proto-grpc>=1.28.0; extra == "opentelemetry"
